joker_stream-0.3-py3.7-nspkg.pth
joker/stream/__init__.py
joker/stream/base.py
joker/stream/shell.py
joker_stream-0.3.dist-info/METADATA
joker_stream-0.3.dist-info/WHEEL
joker_stream-0.3.dist-info/namespace_packages.txt
joker_stream-0.3.dist-info/top_level.txt
joker_stream-0.3.dist-info/RECORD
